winrt/_winrt_windows_media_playback.cp313-win_arm64.pyd
winrt/_winrt_windows_media_playback.pyi
winrt/windows/media/playback/__init__.py
winrt/windows/media/playback/py.typed
winrt_windows_media_playback-3.2.0.dist-info/METADATA
winrt_windows_media_playback-3.2.0.dist-info/WHEEL
winrt_windows_media_playback-3.2.0.dist-info/top_level.txt
winrt_windows_media_playback-3.2.0.dist-info/RECORD
